asynctr/__init__.py
asynctr/__main__.py
asynctr/translate.py
asynctr-0.1.0.dist-info/METADATA
asynctr-0.1.0.dist-info/WHEEL
asynctr-0.1.0.dist-info/top_level.txt
asynctr-0.1.0.dist-info/RECORD
