Metadata-Version: 2.1
Name: asynctr
Version: 0.1.0
Summary: An Asynchronous Google Translate Easy to use API.
Home-page: https://github.com/EraseKesu/asynctr
Author: EraseKesu
Author-email: eitan.olchik@gmail.com
License: UNKNOWN
Platform: UNKNOWN
Classifier: Programming Language :: Python :: 3
Classifier: License :: OSI Approved :: MIT License
Classifier: Operating System :: OS Independent
Requires-Python: >=3.8
